nonebot_plugin_directlinker/__init__.py
nonebot_plugin_directlinker/config.py
nonebot_plugin_directlinker-2.4.0.dist-info/LICENSE
nonebot_plugin_directlinker-2.4.0.dist-info/METADATA
nonebot_plugin_directlinker-2.4.0.dist-info/WHEEL
nonebot_plugin_directlinker-2.4.0.dist-info/top_level.txt
nonebot_plugin_directlinker-2.4.0.dist-info/RECORD
