Metadata-Version: 2.1
Name: nonebot-plugin-directlinker
Version: 2.4.0
Summary: A plugin based on NoneBot2 to extract direct links of files in qq group.
Home-page: https://github.com/Utmost-Happiness-Planet/nonebot-plugin-directlinker
Author: uhpteam
Project-URL: Bug Tracker, https://github.com/Utmost-Happiness-Planet/nonebot-plugin-directlinker/issues
Classifier: Programming Language :: Python :: 3
Classifier: License :: OSI Approved :: GNU General Public License v3 (GPLv3)
Classifier: Operating System :: OS Independent
Requires-Python: >=3.7
License-File: LICENSE
Requires-Dist: nonebot2 (>=2.0.0b2)
Requires-Dist: nonebot-adapter-onebot (>=2.0.0b1)
